setup.py
onestop/__init__.py
onestop/__main__.py
onestop/bootstrap.py
onestop/entities.py
onestop/errors.py
onestop/fetch.py
onestop/geom.py
onestop/registry.py
onestop/stopbins.py
onestop/test_entities.py
onestop/test_geom.py
onestop/test_registry.py
onestop/test_util.py
onestop/util.py
onestop.egg-info/PKG-INFO
onestop.egg-info/SOURCES.txt
onestop.egg-info/dependency_links.txt
onestop.egg-info/not-zip-safe
onestop.egg-info/requires.txt
onestop.egg-info/top_level.txt