Metadata-Version: 1.0
Name: onestop
Version: 0.5.0
Summary: Transitland Onestop
Home-page: https://github.com/transitland/onestop-id-python-client
Author: Ian Rees
Author-email: ian@mapzen.com
License: License :: OSI Approved :: MIT License
Platform: UNKNOWN
